pysole/__init__.py
pysole/colour.py
pysole/console.py
pysole/test.py
pysole/window.py
pysole-0.1.13.dist-info/DESCRIPTION.rst
pysole-0.1.13.dist-info/METADATA
pysole-0.1.13.dist-info/RECORD
pysole-0.1.13.dist-info/WHEEL
pysole-0.1.13.dist-info/metadata.json
pysole-0.1.13.dist-info/top_level.txt
