Metadata-Version: 2.0
Name: pysole
Version: 0.1.13
Summary: pysole is a wrapper for simulating c-sharp console applications on any operating system that supports python.
Home-page: https://github.com/TreeStain/pysole
Author: Tristan Arthur
Author-email: RGSStudios@outlook.com
License: UNKNOWN
Download-URL: https://github.com/TreeStain/pysole/tarball/0.1
Keywords: c-sharp,color,colour,console,display,dynamic,linux,mac,pygame,pysole,pyterm,python3,style,terminal,text,window,windows,wrapper
Platform: UNKNOWN
Requires-Dist: pygame
